intuned_sdk/__init__.py
intuned_sdk/browser_scripts.js
intuned_sdk/computer_use/__init__.py
intuned_sdk/computer_use/common.py
intuned_sdk/computer_use/loop.py
intuned_sdk/computer_use/run_login_task.py
intuned_sdk/computer_use/run_task.py
intuned_sdk/computer_use/run_task_validation.py
intuned_sdk/computer_use/tools/__init__.py
intuned_sdk/computer_use/tools/base.py
intuned_sdk/computer_use/tools/collection.py
intuned_sdk/computer_use/tools/computer.py
intuned_sdk/computer_use/tools/login_tool.py
intuned_sdk/computer_use/tools/planning_tool.py
intuned_sdk/computer_use/tools/playwright_tool.py
intuned_sdk/computer_use/tools/submit_results_tool.py
intuned_sdk/computer_use/tools/validation_function_tool.py
intuned_sdk/computer_use/utils/browser_utils.py
intuned_sdk/computer_use/utils/conversation_utils.py
intuned_sdk/computer_use/utils/print_utils.py
intuned_sdk/convert_locator_to_markdown.py
intuned_sdk/convert_relative_url_to_full_url.py
intuned_sdk/download_file.py
intuned_sdk/execute_actions_on_page.py
intuned_sdk/filter_empty_json.py
intuned_sdk/filter_results_util.py
intuned_sdk/go_to_url.py
intuned_sdk/html_to_markdown_using_ai.py
intuned_sdk/is_page_loaded.py
intuned_sdk/process_dates.py
intuned_sdk/save_file_to_s3.py
intuned_sdk/scroll_to_element.py
intuned_sdk/skills/__init__.py
intuned_sdk/skills/click_element.py
intuned_sdk/skills/enter_text.py
intuned_sdk/skills/enter_text_and_click.py
intuned_sdk/skills/go_to_url.py
intuned_sdk/skills/press_key_combination.py
intuned_sdk/take_safe_screenshot.py
intuned_sdk/upload_file.py
intuned_sdk/utils/__init__.py
intuned_sdk/utils/build_semantic_markdown.py
intuned_sdk/utils/clean_html.py
intuned_sdk/utils/click_button_until_no_change.py
intuned_sdk/utils/dismiss_dialog.py
intuned_sdk/utils/ensure_browser_scripts.py
intuned_sdk/utils/get_mode.py
intuned_sdk/utils/get_page_html.py
intuned_sdk/utils/get_proxy_env.py
intuned_sdk/utils/get_s3_client.py
intuned_sdk/utils/inject_element_ids_into_page.py
intuned_sdk_dev_rauf-0.1.5.dev0.dist-info/LICENSE
intuned_sdk_dev_rauf-0.1.5.dev0.dist-info/METADATA
intuned_sdk_dev_rauf-0.1.5.dev0.dist-info/WHEEL
intuned_sdk_dev_rauf-0.1.5.dev0.dist-info/RECORD
